dask_trino/__init__.py
dask_trino/_version.py
dask_trino/core.py
dask_trino/tests/__init__.py
dask_trino/tests/conftest.py
dask_trino/tests/development_server.py
dask_trino/tests/test_core.py
dask_trino/tests/etc/config.properties
dask_trino/tests/etc/jvm.config
dask_trino/tests/etc/spooling-manager.properties
dask_trino/tests/etc/catalog/memory.properties
dask_trino/tests/etc/catalog/tpch.properties
dask_trino-0.2.0.dist-info/LICENSE
dask_trino-0.2.0.dist-info/METADATA
dask_trino-0.2.0.dist-info/WHEEL
dask_trino-0.2.0.dist-info/top_level.txt
dask_trino-0.2.0.dist-info/RECORD
