Metadata-Version: 2.2
Name: dask-trino
Version: 0.2.0
Summary: Dask + Trino integration
Home-page: https://github.com/posulliv/dask-trino
Author: Padraig O'Sullivan
Author-email: padraig.osullivan@starburstdata.com
License: Apache 2.0
Requires-Python: >=3.10
License-File: LICENSE
Requires-Dist: dask>=2024.3.0
Requires-Dist: distributed
Requires-Dist: trino>=0.333.0
Requires-Dist: trino[sqlalchemy]
Provides-Extra: tests
Requires-Dist: pytest; extra == "tests"
Requires-Dist: pytest-runner; extra == "tests"
Requires-Dist: pre-commit; extra == "tests"
Requires-Dist: black; extra == "tests"
Requires-Dist: isort; extra == "tests"
Requires-Dist: keyring; extra == "tests"
Requires-Dist: testcontainers; extra == "tests"
Requires-Dist: boto3; extra == "tests"
Requires-Dist: pandas; extra == "tests"
Requires-Dist: pyarrow; extra == "tests"
Dynamic: author
Dynamic: author-email
Dynamic: description
Dynamic: description-content-type
Dynamic: home-page
Dynamic: license
Dynamic: provides-extra
Dynamic: requires-dist
Dynamic: requires-python
Dynamic: summary
